climex/__init__.py
climex/base.py
climex/climex.py
climex/config.py
climex/geo.py
climex/klimdex.py
climex/normal.py
climex/project.py
climex/qc.py
climex/station.py
climex/stats.py
climex-0.5.3.dist-info/LICENSE
climex-0.5.3.dist-info/METADATA
climex-0.5.3.dist-info/WHEEL
climex-0.5.3.dist-info/top_level.txt
climex-0.5.3.dist-info/RECORD
