Metadata-Version: 2.1
Name: climex
Version: 0.5.3
Summary: A package to download and process climate data from México
Author-email: Ángel Marqués-Mateu <amarques@cgf.upv.es>
Project-URL: Homepage, http://personales.upv.es/amarques/climex
Classifier: Programming Language :: Python :: 3
Classifier: License :: OSI Approved :: European Union Public Licence 1.2 (EUPL 1.2)
Classifier: Operating System :: OS Independent
Requires-Python: >=3.7
License-File: LICENSE
Requires-Dist: requests
Requires-Dist: easygui
Requires-Dist: pyshp
Requires-Dist: matplotlib
Requires-Dist: folium
